fasttea.pypy38-pp73-x86_64-linux-gnu.so
fasttea-1.1.0.dist-info/WHEEL
fasttea-1.1.0.dist-info/RECORD
fasttea-1.1.0.dist-info/top_level.txt
fasttea-1.1.0.dist-info/METADATA
