Metadata-Version: 2.1
Name: fasttea
Version: 1.1.0
Summary: Fast XiaoTea encryption and decryption
Home-page: UNKNOWN
Author: Daljeet Nandha
License: UNKNOWN
Platform: UNKNOWN
Classifier: Programming Language :: Python :: 3
Classifier: Programming Language :: C
Classifier: License :: OSI Approved :: MIT License
Classifier: Operating System :: OS Independent
